s2s_connector/__init__.py
s2s_connector/connector.py
s2s_connector-0.0.3.dist-info/METADATA
s2s_connector-0.0.3.dist-info/WHEEL
s2s_connector-0.0.3.dist-info/RECORD
