Metadata-Version: 2.1
Name: s2s-connector
Version: 0.0.3
Summary: A general-purpose Service-to-Service (S2S) connector for obtaining bearer tokens for authentication in service-to-service communication.
Author: Pavel Mulin
Author-email: mulin.pasha@gmail.com
Requires-Python: >=3.9.0
Classifier: Programming Language :: Python :: 3
Classifier: Programming Language :: Python :: 3.9
Classifier: Programming Language :: Python :: 3.10
Classifier: Programming Language :: Python :: 3.11
Classifier: Programming Language :: Python :: 3.12
Requires-Dist: httpx (>=0.23.0)
